notion_nlp/__init__.py
notion_nlp/__main__.py
notion_nlp/core/__init__.py
notion_nlp/core/api.py
notion_nlp/core/nlp.py
notion_nlp/core/task.py
notion_nlp/core/visual.py
notion_nlp/parameter/__init__.py
notion_nlp/parameter/config.py
notion_nlp/parameter/error.py
notion_nlp/parameter/log.py
notion_nlp/parameter/utils.py
notion_nlp-1.0.7.3.dist-info/LICENSE
notion_nlp-1.0.7.3.dist-info/WHEEL
notion_nlp-1.0.7.3.dist-info/METADATA
notion_nlp-1.0.7.3.dist-info/RECORD
