Metadata-Version: 2.1
Name: notion-nlp
Version: 1.0.7.3
Summary: Reading rich text information from a Notion database and performing simple NLP analysis.
License: MIT
Author: Dario Zhang
Author-email: zdclink@gmail.com
Requires-Python: >=3.8.10,<3.12
Classifier: License :: OSI Approved :: MIT License
Classifier: Programming Language :: Python :: 3
Classifier: Programming Language :: Python :: 3.9
Classifier: Programming Language :: Python :: 3.10
Classifier: Programming Language :: Python :: 3.11
Provides-Extra: doc
Requires-Dist: arrow (==1.2.3)
Requires-Dist: jieba (==0.42.1)
Requires-Dist: matplotlib (==3.7.0)
Requires-Dist: pandas (==1.5.3)
Requires-Dist: pydantic (==1.10.5)
Requires-Dist: requests (==2.28.2)
Requires-Dist: ruamel-yaml (==0.17.21)
Requires-Dist: scikit-learn (==1.2.1)
Requires-Dist: tabulate (==0.9.0)
Requires-Dist: toolz (==0.12.0)
Requires-Dist: tqdm (==4.64.1)
Requires-Dist: typer (==0.7.0)
Requires-Dist: wcwidth (==0.2.6)
Requires-Dist: wordcloud (==1.8.2.2)
